rolch/__init__.py
rolch/coordinate_descent.py
rolch/design_matrix.py
rolch/error.py
rolch/gram.py
rolch/information_criteria.py
rolch/scaler.py
rolch/utils.py
rolch/warnings.py
rolch/base/__init__.py
rolch/base/distribution.py
rolch/base/estimation_method.py
rolch/base/estimator.py
rolch/base/link.py
rolch/distributions/__init__.py
rolch/distributions/gamma.py
rolch/distributions/johnsonsu.py
rolch/distributions/lognormal.py
rolch/distributions/lognormalmedian.py
rolch/distributions/normal.py
rolch/distributions/studentt.py
rolch/estimators/__init__.py
rolch/estimators/online_gamlss.py
rolch/estimators/online_lasso.py
rolch/estimators/online_linear_model.py
rolch/link/__init__.py
rolch/link/identitylinks.py
rolch/link/loglinks.py
rolch/link/robust_math.py
rolch/link/softpluslinks.py
rolch/link/sqrtlinks.py
rolch/methods/__init__.py
rolch/methods/elasticnet.py
rolch/methods/factory.py
rolch/methods/lasso_path.py
rolch/methods/recursive_least_squares.py
rolch/methods/ridge.py
rolch-0.2.5.dist-info/licenses/LICENSE.txt
rolch-0.2.5.dist-info/METADATA
rolch-0.2.5.dist-info/WHEEL
rolch-0.2.5.dist-info/top_level.txt
rolch-0.2.5.dist-info/RECORD
